msea/__init__.py
msea/set_library.py
msea/utils.py
tests/__init__.py
tests/test_enrich.py
tests/test_set_library.py
msea-0.0.2.dist-info/LICENSE
msea-0.0.2.dist-info/METADATA
msea-0.0.2.dist-info/WHEEL
msea-0.0.2.dist-info/top_level.txt
msea-0.0.2.dist-info/RECORD
