Metadata-Version: 2.1
Name: msea
Version: 0.0.2
Summary: Implementation of Microbe-Set Enrichment Analysis (MSEA).
Home-page: https://bitbucket.com/wangz10/msea
Author: Zichen Wang
Author-email: wangzc921@gmail.com
License: BSD
Platform: UNKNOWN
Classifier: Programming Language :: Python :: 3
Classifier: License :: OSI Approved :: BSD License
Classifier: Operating System :: OS Independent
Requires-Python: >=3.5
Requires-Dist: numpy
Requires-Dist: pandas
Requires-Dist: scipy
Requires-Dist: tqdm
